[
{"id":"p1091","de":{"word":"möbliert","ipa":"[møˈbliːɐ̯t]","examples":[{"s":"Wir suchen eine möblierte Wohnung für ein halbes Jahr.","zh":"我們找一間附家具的公寓,租半年。"},{"s":"Das Zimmer ist komplett möbliert, du musst nichts mitbringen.","zh":"這房間完全附家具,你什麼都不用帶。"}]},"fr":{"word":"meublé","ipa":"[mœble]","examples":[{"s":"Nous louons un appartement meublé près du centre.","zh":"我們在市中心附近租了一間附家具的公寓。"},{"s":"Le studio est déjà meublé, il y a même un lave-linge.","zh":"這間套房已經附家具,甚至還有洗衣機。"}]},"ja":{"word":"家具付き","kana":"かぐつき","romaji":"kagutsuki","examples":[{"s":"家具付きの部屋なので、すぐに住めます。","zh":"因為是附家具的房間,馬上就能入住。"},{"s":"この物件は家具付きで家賃も手頃です。","zh":"這個房子附家具,租金也很合理。"}]}},
{"id":"p1092","de":{"word":"die Möbel","ipa":"[ˈmøːbl̩]","examples":[{"s":"Wir müssen neue Möbel für das Wohnzimmer kaufen.","zh":"我們得為客廳買新家具。"},{"s":"Die alten Möbel geben wir an einen Freund weiter.","zh":"這些舊家具我們轉送給一個朋友。"}]},"fr":{"word":"le meuble","ipa":"[mœbl]","examples":[{"s":"Nous avons acheté de nouveaux meubles pour le salon.","zh":"我們為客廳買了新家具。"},{"s":"Ces meubles sont trop lourds à déplacer seul.","zh":"這些家具太重了,一個人搬不動。"}]},"ja":{"word":"家具","kana":"かぐ","romaji":"kagu","examples":[{"s":"新しい家具を買って部屋の雰囲気を変えました。","zh":"買了新家具,改變了房間的氛圍。"},{"s":"引っ越しのとき、家具を全部運ぶのは大変でした。","zh":"搬家的時候,把全部家具搬走很辛苦。"}]}},
{"id":"p1093","de":{"word":"Bezug nehmend auf","ipa":"[bəˈtsuːk ˈneːmənt aʊ̯f]","examples":[{"s":"Bezug nehmend auf Ihre E-Mail sende ich Ihnen die Unterlagen.","zh":"承接您的電子郵件,我把文件寄給您。"},{"s":"Bezug nehmend auf unser Gespräch möchte ich einen Termin vereinbaren.","zh":"關於我們先前的談話,我想約個時間。"}]},"fr":{"word":"suite à","ipa":"[sɥit a]","examples":[{"s":"Suite à votre message, je vous envoie les documents demandés.","zh":"承接您的訊息,我把您要求的文件寄給您。"},{"s":"Suite à notre discussion, voici les détails du projet.","zh":"關於我們先前的討論,這是專案的細節。"}]},"ja":{"word":"に関して","kana":"にかんして","romaji":"ni kanshite","examples":[{"s":"先日のメールに関して、資料をお送りします。","zh":"承接前幾天的郵件,我把資料寄給您。"},{"s":"前回の話に関して、もう一度確認したいことがあります。","zh":"關於上次的談話,我有件事想再確認。"}]}},
{"id":"p1094","de":{"word":"das Quengeln","ipa":"[ˈkvɛŋl̩n]","examples":[{"s":"Das Baby fängt vor dem Schlafen oft an zu quengeln.","zh":"寶寶睡前常常開始哭鬧。"},{"s":"Mach kein Theater, wir gehen gleich nach Hause.","zh":"別鬧了,我們馬上就回家。"}]},"fr":{"word":"le caprice","ipa":"[kapʁis]","examples":[{"s":"L'enfant fait un caprice parce qu'il est fatigué.","zh":"孩子在哭鬧,因為他累了。"},{"s":"Arrête de râler, on part dans cinq minutes.","zh":"別再煩躁了,我們五分鐘後就走。"}]},"ja":{"word":"ぐずる","kana":"ぐずる","romaji":"guzuru","examples":[{"s":"赤ちゃんが眠くてぐずっています。","zh":"寶寶想睡,正在哭鬧。"},{"s":"子どもがおもちゃ屋の前でぐずって動きません。","zh":"孩子在玩具店前哭鬧不肯走。"}]}},
{"id":"p1095","de":{"word":"flauschig","ipa":"[ˈflaʊ̯ʃɪç]","examples":[{"s":"Die neue Decke ist so schön flauschig und warm.","zh":"這條新毯子好毛茸茸又溫暖。"},{"s":"Der kleine Hund hat ein flauschiges Fell.","zh":"這隻小狗有一身毛茸茸的毛。"}]},"fr":{"word":"duveteux","ipa":"[dyvtø]","examples":[{"s":"Cette couverture est toute douce et duveteuse.","zh":"這條毯子又柔軟又毛茸茸的。"},{"s":"Le chaton a un pelage tout duveteux.","zh":"這隻小貓有一身毛茸茸的毛。"}]},"ja":{"word":"ふわふわ","kana":"ふわふわ","romaji":"fuwafuwa","examples":[{"s":"このタオルはふわふわで気持ちいいです。","zh":"這條毛巾毛茸茸的,很舒服。"},{"s":"ふわふわのぬいぐるみを抱いて眠りました。","zh":"抱著毛茸茸的娃娃睡著了。"}]}},
{"id":"p1096","de":{"word":"die Galaxie","ipa":"[ɡalaˈksiː]","examples":[{"s":"Unsere Galaxie heißt die Milchstraße.","zh":"我們的星系叫做銀河系。"},{"s":"Im Universum gibt es unzählige Galaxien.","zh":"宇宙中有無數的星系。"}]},"fr":{"word":"la galaxie","ipa":"[ɡalaksi]","examples":[{"s":"Notre galaxie s'appelle la Voie lactée.","zh":"我們的星系叫做銀河系。"},{"s":"Le télescope a photographié une galaxie lointaine.","zh":"望遠鏡拍到了一個遙遠的星系。"}]},"ja":{"word":"銀河","kana":"ぎんが","romaji":"ginga","examples":[{"s":"私たちの銀河は天の川と呼ばれています。","zh":"我們的星系被稱為銀河。"},{"s":"宇宙にはたくさんの銀河があります。","zh":"宇宙中有許多星系。"}]}},
{"id":"p1097","de":{"word":"der Galaxienhaufen","ipa":"[ɡalaˈksiːənˌhaʊ̯fn̩]","examples":[{"s":"Ein Galaxienhaufen enthält Hunderte von Galaxien.","zh":"一個星系團包含數百個星系。"},{"s":"Astronomen untersuchen die Schwerkraft in einem Galaxienhaufen.","zh":"天文學家研究星系團中的重力。"}]},"fr":{"word":"l'amas de galaxies","ipa":"[ama də ɡalaksi]","examples":[{"s":"Cet amas de galaxies se trouve à des millions d'années-lumière.","zh":"這個星系團位於數百萬光年之外。"},{"s":"L'amas de galaxies est maintenu ensemble par la gravité.","zh":"星系團靠重力聚在一起。"}]},"ja":{"word":"銀河団","kana":"ぎんがだん","romaji":"gingadan","examples":[{"s":"銀河団は数百の銀河から成り立っています。","zh":"星系團由數百個星系組成。"},{"s":"研究者は遠くの銀河団を観測しました。","zh":"研究者觀測了遠方的星系團。"}]}},
{"id":"p1098","de":{"word":"die Galerie","ipa":"[ɡaləˈriː]","examples":[{"s":"Am Wochenende besuchen wir eine Galerie in der Altstadt.","zh":"週末我們去參觀老城區的一間畫廊。"},{"s":"In der Galerie hängen Werke junger Künstler.","zh":"畫廊裡掛著年輕藝術家的作品。"}]},"fr":{"word":"la galerie","ipa":"[ɡalʁi]","examples":[{"s":"Nous avons visité une galerie d'art moderne hier.","zh":"我們昨天參觀了一間現代藝術畫廊。"},{"s":"Cette galerie expose des peintures locales.","zh":"這間畫廊展出當地的畫作。"}]},"ja":{"word":"画廊","kana":"がろう","romaji":"garō","examples":[{"s":"週末に小さな画廊で絵を見てきました。","zh":"週末去一間小畫廊看了畫。"},{"s":"この画廊では若い作家の作品を展示しています。","zh":"這間畫廊展示年輕創作者的作品。"}]}},
{"id":"p1099","de":{"word":"galoppieren","ipa":"[ɡalɔˈpiːʁən]","examples":[{"s":"Das Pferd galoppierte über die weite Wiese.","zh":"那匹馬在廣闊的草地上疾馳。"},{"s":"Die Kinder sahen zu, wie die Pferde galoppierten.","zh":"孩子們看著馬兒飛奔。"}]},"fr":{"word":"galoper","ipa":"[ɡalɔpe]","examples":[{"s":"Le cheval galope à travers le champ.","zh":"那匹馬在田野上疾馳。"},{"s":"Elle aime galoper sur la plage au lever du soleil.","zh":"她喜歡在日出時於海灘上飛奔。"}]},"ja":{"word":"疾走する","kana":"しっそうする","romaji":"shissō suru","examples":[{"s":"馬が草原を疾走していきました。","zh":"馬在草原上疾馳而去。"},{"s":"競馬場で馬が一斉に疾走を始めた。","zh":"賽馬場上馬匹一齊開始飛奔。"}]}},
{"id":"p1100","de":{"word":"das Spiel","ipa":"[ʃpiːl]","examples":[{"s":"Wir schauen uns heute Abend das Spiel im Fernsehen an.","zh":"我們今晚要在電視上看比賽。"},{"s":"Die Kinder spielen ein lustiges Spiel im Garten.","zh":"孩子們在花園裡玩一個有趣的遊戲。"}]},"fr":{"word":"le jeu","ipa":"[ʒø]","examples":[{"s":"Ce soir, nous regardons le jeu à la télévision.","zh":"今晚我們在電視上看比賽。"},{"s":"Les enfants adorent ce jeu de société.","zh":"孩子們很喜歡這個桌上遊戲。"}]},"ja":{"word":"試合","kana":"しあい","romaji":"shiai","examples":[{"s":"今夜はテレビで試合を見るつもりです。","zh":"今晚我打算在電視上看比賽。"},{"s":"友達と公園でゲームをして遊びました。","zh":"和朋友在公園玩遊戲。"}]}},
{"id":"p1101","de":{"word":"die Bande","ipa":"[ˈbandə]","examples":[{"s":"Die Polizei hat eine kriminelle Bande festgenommen.","zh":"警方逮捕了一個犯罪幫派。"},{"s":"In dieser Gegend gibt es Probleme mit einer Bande.","zh":"這一帶有幫派引發的問題。"}]},"fr":{"word":"le gang","ipa":"[ɡɑ̃ɡ]","examples":[{"s":"La police a arrêté les membres du gang.","zh":"警方逮捕了幫派成員。"},{"s":"Ce quartier était autrefois contrôlé par un gang.","zh":"這個街區以前曾被一個幫派控制。"}]},"ja":{"word":"ギャング","kana":"ギャング","romaji":"gyangu","examples":[{"s":"警察がギャングの一味を逮捕しました。","zh":"警察逮捕了一夥幫派分子。"},{"s":"この地域はギャングの犯罪で有名でした。","zh":"這個地區曾以幫派犯罪聞名。"}]}},
{"id":"p1102","de":{"word":"die Garage","ipa":"[ɡaˈʁaːʒə]","examples":[{"s":"Ich stelle das Auto abends immer in die Garage.","zh":"我晚上總是把車停進車庫。"},{"s":"In der Garage lagern wir auch alte Fahrräder.","zh":"我們也把舊腳踏車放在車庫裡。"}]},"fr":{"word":"le garage","ipa":"[ɡaʁaʒ]","examples":[{"s":"Je gare la voiture dans le garage chaque soir.","zh":"我每天晚上把車停進車庫。"},{"s":"Le garage est plein d'outils et de cartons.","zh":"車庫裡堆滿了工具和紙箱。"}]},"ja":{"word":"車庫","kana":"しゃこ","romaji":"shako","examples":[{"s":"夜は車を車庫に入れています。","zh":"晚上我把車停進車庫。"},{"s":"車庫には古い自転車も置いてあります。","zh":"車庫裡也放著舊腳踏車。"}]}},
{"id":"p1103","de":{"word":"garnieren","ipa":"[ɡaʁˈniːʁən]","examples":[{"s":"Der Koch garniert den Teller mit frischen Kräutern.","zh":"廚師用新鮮香草裝飾盤子。"},{"s":"Wir garnieren den Kuchen mit ein paar Erdbeeren.","zh":"我們用幾顆草莓裝飾蛋糕。"}]},"fr":{"word":"garnir","ipa":"[ɡaʁniʁ]","examples":[{"s":"Le chef garnit le plat avec du persil frais.","zh":"主廚用新鮮巴西里裝飾這道菜。"},{"s":"On garnit le dessert de quelques fruits rouges.","zh":"我們用幾顆紅色莓果裝飾甜點。"}]},"ja":{"word":"添える","kana":"そえる","romaji":"soeru","examples":[{"s":"料理にハーブを添えると見た目がきれいです。","zh":"在料理上點綴香草,看起來很漂亮。"},{"s":"ケーキにイチゴを添えて仕上げました。","zh":"用草莓裝飾蛋糕收尾。"}]}},
{"id":"p1104","de":{"word":"das Benzin","ipa":"[bɛnˈtsiːn]","examples":[{"s":"Wir müssen unterwegs noch Benzin tanken.","zh":"我們路上還得加油。"},{"s":"Das Benzin ist in letzter Zeit teurer geworden.","zh":"汽油最近變貴了。"}]},"fr":{"word":"l'essence","ipa":"[esɑ̃s]","examples":[{"s":"Il faut mettre de l'essence avant le départ.","zh":"出發前得先加油。"},{"s":"Le prix de l'essence a beaucoup augmenté.","zh":"汽油價格漲了很多。"}]},"ja":{"word":"ガソリン","kana":"ガソリン","romaji":"gasorin","examples":[{"s":"出発する前にガソリンを入れておきましょう。","zh":"出發前先加點油吧。"},{"s":"最近ガソリンの値段が高くなりました。","zh":"最近汽油的價格變貴了。"}]}},
{"id":"p1105","de":{"word":"die Tankstelle","ipa":"[ˈtaŋkʃtɛlə]","examples":[{"s":"An der nächsten Tankstelle halten wir kurz an.","zh":"我們在下一個加油站稍微停一下。"},{"s":"Die Tankstelle hat rund um die Uhr geöffnet.","zh":"這家加油站二十四小時營業。"}]},"fr":{"word":"la station-service","ipa":"[stasjɔ̃ sɛʁvis]","examples":[{"s":"Arrêtons-nous à la station-service pour faire le plein.","zh":"我們在加油站停下來加滿油吧。"},{"s":"Il y a une station-service juste après le pont.","zh":"過了橋就有一間加油站。"}]},"ja":{"word":"ガソリンスタンド","kana":"ガソリンスタンド","romaji":"gasorin sutando","examples":[{"s":"次のガソリンスタンドで給油しましょう。","zh":"在下一個加油站加油吧。"},{"s":"この道沿いにガソリンスタンドがあります。","zh":"這條路旁有一間加油站。"}]}},
{"id":"p1106","de":{"word":"das Gate","ipa":"[ɡeɪ̯t]","examples":[{"s":"Unser Flug geht von Gate zwölf ab.","zh":"我們的班機從十二號登機門起飛。"},{"s":"Bitte begeben Sie sich rechtzeitig zum Gate.","zh":"請準時前往登機門。"}]},"fr":{"word":"la porte d'embarquement","ipa":"[pɔʁt dɑ̃baʁkəmɑ̃]","examples":[{"s":"L'embarquement se fait à la porte numéro huit.","zh":"在八號登機門登機。"},{"s":"Nous devons courir vers la porte d'embarquement.","zh":"我們得跑向登機門。"}]},"ja":{"word":"搭乗口","kana":"とうじょうぐち","romaji":"tōjōguchi","examples":[{"s":"搭乗口は十番ですので、お急ぎください。","zh":"登機門是十號,請趕快。"},{"s":"搭乗口の近くで待っていてください。","zh":"請在登機門附近等候。"}]}},
{"id":"p1107","de":{"word":"sich versammeln","ipa":"[fɛɐ̯ˈzaml̩n]","examples":[{"s":"Die ganze Familie versammelt sich zum Abendessen.","zh":"全家人聚在一起吃晚餐。"},{"s":"Am Platz versammeln sich viele Menschen für das Fest.","zh":"許多人聚集在廣場上參加慶典。"}]},"fr":{"word":"se rassembler","ipa":"[sə ʁasɑ̃ble]","examples":[{"s":"Toute la famille se rassemble pour le dîner.","zh":"全家人聚在一起吃晚餐。"},{"s":"Les gens se rassemblent sur la place pour la fête.","zh":"人們聚集在廣場上慶祝節日。"}]},"ja":{"word":"集まる","kana":"あつまる","romaji":"atsumaru","examples":[{"s":"家族みんなで夕食に集まりました。","zh":"全家人聚在一起吃晚餐。"},{"s":"広場に大勢の人が集まっています。","zh":"許多人聚集在廣場上。"}]}},
{"id":"p1108","de":{"word":"anstarren","ipa":"[ˈanˌʃtaʁən]","examples":[{"s":"Sie starrte lange gedankenverloren aus dem Fenster.","zh":"她出神地望著窗外好一會兒。"},{"s":"Bitte starr die Leute nicht so an, das ist unhöflich.","zh":"請不要那樣盯著別人看,這樣不禮貌。"}]},"fr":{"word":"fixer","ipa":"[fikse]","examples":[{"s":"Elle fixe l'horizon sans dire un mot.","zh":"她凝視著地平線,一句話也不說。"},{"s":"Il fixait l'écran, complètement absorbé.","zh":"他注視著螢幕,完全入迷。"}]},"ja":{"word":"見つめる","kana":"みつめる","romaji":"mitsumeru","examples":[{"s":"彼女はしばらく窓の外を見つめていました。","zh":"她凝視著窗外好一陣子。"},{"s":"星空をじっと見つめていると時間を忘れます。","zh":"注視著星空,會忘記時間。"}]}},
{"id":"p1109","de":{"word":"die Ausrüstung","ipa":"[ˈaʊ̯sˌʁʏstʊŋ]","examples":[{"s":"Vor der Wanderung prüfen wir die ganze Ausrüstung.","zh":"健行前我們檢查全部裝備。"},{"s":"Für den Tauchkurs braucht man spezielle Ausrüstung.","zh":"潛水課需要特別的裝備。"}]},"fr":{"word":"l'équipement","ipa":"[ekipmɑ̃]","examples":[{"s":"Nous vérifions notre équipement avant la randonnée.","zh":"健行前我們檢查裝備。"},{"s":"L'équipement de camping est déjà dans la voiture.","zh":"露營裝備已經放進車裡了。"}]},"ja":{"word":"装備","kana":"そうび","romaji":"sōbi","examples":[{"s":"登山の前に装備をすべて確認します。","zh":"登山前把裝備全部確認一遍。"},{"s":"キャンプ用の装備を車に積み込みました。","zh":"把露營用的裝備裝進了車裡。"}]}},
{"id":"p1110","de":{"word":"der Edelstein","ipa":"[ˈeːdl̩ʃtaɪ̯n]","examples":[{"s":"Der Ring ist mit einem funkelnden Edelstein besetzt.","zh":"這枚戒指鑲著一顆閃亮的寶石。"},{"s":"Im Museum sind viele seltene Edelsteine ausgestellt.","zh":"博物館裡展出許多稀有的寶石。"}]},"fr":{"word":"le joyau","ipa":"[ʒwajo]","examples":[{"s":"Cette couronne est ornée de nombreux joyaux.","zh":"這頂王冠鑲滿了許多寶石。"},{"s":"Elle garde ses joyaux dans un coffre-fort.","zh":"她把寶石收在保險箱裡。"}]},"ja":{"word":"宝石","kana":"ほうせき","romaji":"hōseki","examples":[{"s":"指輪には美しい宝石がはめ込まれています。","zh":"戒指上鑲著美麗的寶石。"},{"s":"博物館で珍しい宝石を見ました。","zh":"在博物館看到了稀有的寶石。"}]}},
{"id":"p1111","de":{"word":"der Edelstein","ipa":"[ˈeːdl̩ʃtaɪ̯n]","examples":[{"s":"Dieser rohe Edelstein muss noch geschliffen werden.","zh":"這顆原石寶石還需要打磨。"},{"s":"Ein einzelner Edelstein kann sehr wertvoll sein.","zh":"單獨一顆寶石可能非常值錢。"}]},"fr":{"word":"la pierre précieuse","ipa":"[pjɛʁ pʁesjøz]","examples":[{"s":"Le bijoutier examine la pierre précieuse à la loupe.","zh":"珠寶商用放大鏡檢視那顆寶石。"},{"s":"Cette pierre précieuse vient d'une mine lointaine.","zh":"這顆寶石來自一座遙遠的礦場。"}]},"ja":{"word":"原石","kana":"げんせき","romaji":"genseki","examples":[{"s":"この宝石の原石はまだ磨かれていません。","zh":"這顆寶石原石還沒被打磨。"},{"s":"一粒の原石が驚くほど高く売れました。","zh":"單顆原石賣出了驚人的高價。"}]}},
{"id":"p1112","de":{"word":"allgemein","ipa":"[ˈalɡəˌmaɪ̯n]","examples":[{"s":"Das ist eine allgemein bekannte Tatsache.","zh":"這是一個眾所周知的普遍事實。"},{"s":"Im Allgemeinen bin ich mit dem Ergebnis zufrieden.","zh":"一般來說,我對結果很滿意。"}]},"fr":{"word":"général","ipa":"[ʒeneʁal]","examples":[{"s":"En général, je me lève tôt le matin.","zh":"一般來說,我早上很早起床。"},{"s":"C'est une opinion assez générale dans le pays.","zh":"這在這個國家是相當普遍的看法。"}]},"ja":{"word":"一般的な","kana":"いっぱんてきな","romaji":"ippanteki na","examples":[{"s":"これは一般的によく知られている事実です。","zh":"這是一般廣為人知的事實。"},{"s":"一般的に言えば、その方法が一番簡単です。","zh":"一般來說,那個方法最簡單。"}]}},
{"id":"p1113","de":{"word":"erzeugen","ipa":"[ɛɐ̯ˈtsɔɪ̯ɡn̩]","examples":[{"s":"Solarzellen erzeugen Strom aus Sonnenlicht.","zh":"太陽能板從陽光產生電力。"},{"s":"Das Kraftwerk erzeugt Energie für die ganze Stadt.","zh":"這座發電廠為整座城市發電。"}]},"fr":{"word":"produire","ipa":"[pʁɔdɥiʁ]","examples":[{"s":"Ces panneaux solaires produisent de l'électricité.","zh":"這些太陽能板產生電力。"},{"s":"L'usine produit de l'énergie pour la région.","zh":"這座工廠為這個地區發電。"}]},"ja":{"word":"発生させる","kana":"はっせいさせる","romaji":"hassei saseru","examples":[{"s":"太陽光パネルは電気を発生させます。","zh":"太陽能板會產生電力。"},{"s":"この発電所は町全体の電力を生み出しています。","zh":"這座發電廠為整座城鎮發電。"}]}},
{"id":"p1114","de":{"word":"die Generation","ipa":"[ɡenəʁaˈt͡si̯oːn]","examples":[{"s":"Die jüngere Generation nutzt ganz andere Technik.","zh":"年輕世代使用完全不同的科技。"},{"s":"Diese Tradition wird von Generation zu Generation weitergegeben.","zh":"這個傳統一代一代地傳承下去。"}]},"fr":{"word":"la génération","ipa":"[ʒeneʁasjɔ̃]","examples":[{"s":"La nouvelle génération grandit avec les smartphones.","zh":"新世代是伴隨著智慧型手機長大的。"},{"s":"Cette recette se transmet de génération en génération.","zh":"這道食譜一代一代地流傳下來。"}]},"ja":{"word":"世代","kana":"せだい","romaji":"sedai","examples":[{"s":"若い世代はまったく違う考え方をします。","zh":"年輕世代有著完全不同的想法。"},{"s":"この伝統は世代から世代へ受け継がれています。","zh":"這個傳統一代一代地傳承下去。"}]}},
{"id":"p1115","de":{"word":"großzügig","ipa":"[ˈɡʁoːsˌtsyːɡɪç]","examples":[{"s":"Meine Großmutter ist sehr großzügig mit Geschenken.","zh":"我的祖母送禮物非常慷慨。"},{"s":"Er hat großzügig für die Hilfsaktion gespendet.","zh":"他慷慨地為救助行動捐了款。"}]},"fr":{"word":"généreux","ipa":"[ʒeneʁø]","examples":[{"s":"Elle est très généreuse avec ses amis.","zh":"她對朋友非常慷慨。"},{"s":"Ils ont fait un don généreux à l'association.","zh":"他們慷慨地捐款給協會。"}]},"ja":{"word":"気前がいい","kana":"きまえがいい","romaji":"kimae ga ii","examples":[{"s":"祖母はいつも気前よくお小遣いをくれます。","zh":"祖母總是很慷慨地給零用錢。"},{"s":"彼は気前よく寄付をしてくれました。","zh":"他慷慨地捐了款。"}]}},
{"id":"p1116","de":{"word":"das Genre","ipa":"[ˈʒɑ̃ːʁə]","examples":[{"s":"Welches Filmgenre magst du am liebsten?","zh":"你最喜歡哪種電影類型?"},{"s":"Dieser Song passt in kein bestimmtes Genre.","zh":"這首歌不屬於任何特定的類型。"}]},"fr":{"word":"le genre","ipa":"[ʒɑ̃ʁ]","examples":[{"s":"Quel genre de films préfères-tu ?","zh":"你比較喜歡哪種類型的電影?"},{"s":"Cette série mélange plusieurs genres.","zh":"這部影集混合了好幾種類型。"}]},"ja":{"word":"ジャンル","kana":"ジャンル","romaji":"janru","examples":[{"s":"どんなジャンルの映画が好きですか。","zh":"你喜歡哪種類型的電影?"},{"s":"この曲はどのジャンルにも当てはまりません。","zh":"這首歌不屬於任何類型。"}]}},
{"id":"p1117","de":{"word":"sanft","ipa":"[zanft]","examples":[{"s":"Sie streichelte das Kätzchen ganz sanft.","zh":"她非常溫柔地撫摸小貓。"},{"s":"Er sprach mit einer sanften, ruhigen Stimme.","zh":"他用溫柔平靜的聲音說話。"}]},"fr":{"word":"doux","ipa":"[du]","examples":[{"s":"Elle caresse doucement le chaton.","zh":"她溫柔地撫摸小貓。"},{"s":"Il a une voix douce et rassurante.","zh":"他的聲音溫柔又令人安心。"}]},"ja":{"word":"優しい","kana":"やさしい","romaji":"yasashii","examples":[{"s":"彼女は優しく子猫をなでました。","zh":"她溫柔地撫摸小貓。"},{"s":"優しい声で赤ちゃんに話しかけました。","zh":"用溫柔的聲音對寶寶說話。"}]}},
{"id":"p1118","de":{"word":"geothermisch","ipa":"[ɡeoˈtɛʁmɪʃ]","examples":[{"s":"Island nutzt viel geothermische Energie.","zh":"冰島大量利用地熱能源。"},{"s":"Das Haus wird mit geothermischer Wärme geheizt.","zh":"這棟房子用地熱供暖。"}]},"fr":{"word":"géothermique","ipa":"[ʒeɔtɛʁmik]","examples":[{"s":"L'Islande produit beaucoup d'énergie géothermique.","zh":"冰島生產大量地熱能源。"},{"s":"Ils chauffent la maison avec une pompe géothermique.","zh":"他們用地熱幫浦為房子供暖。"}]},"ja":{"word":"地熱の","kana":"ちねつの","romaji":"chinetsu no","examples":[{"s":"アイスランドは地熱のエネルギーを多く使っています。","zh":"冰島大量使用地熱能源。"},{"s":"この施設は地熱の熱で暖房をしています。","zh":"這座設施用地熱供暖。"}]}},
{"id":"p1119","de":{"word":"auskommen","ipa":"[ˈaʊ̯sˌkɔmən]","examples":[{"s":"Die beiden Nachbarn kommen sehr gut miteinander aus.","zh":"這兩位鄰居相處得非常融洽。"},{"s":"Ich komme mit meinen Kollegen prima aus.","zh":"我和同事相處得很好。"}]},"fr":{"word":"s'entendre","ipa":"[sɑ̃tɑ̃dʁ]","examples":[{"s":"Les deux voisins s'entendent très bien.","zh":"這兩位鄰居相處得很好。"},{"s":"Je m'entends bien avec toute l'équipe.","zh":"我和整個團隊都相處融洽。"}]},"ja":{"word":"仲良くする","kana":"なかよくする","romaji":"nakayoku suru","examples":[{"s":"隣同士がとても仲良くしています。","zh":"鄰居之間相處得很融洽。"},{"s":"職場の人たちと仲良くやっています。","zh":"我和職場的人相處得很好。"}]}},
{"id":"p1120","de":{"word":"auskommen mit","ipa":"[ˈaʊ̯sˌkɔmən mɪt]","examples":[{"s":"Ich komme gut mit meinen neuen Kollegen aus.","zh":"我和新同事相處融洽。"},{"s":"Sie kommt bestens mit ihrer Schwiegermutter aus.","zh":"她和婆婆相處得非常好。"}]},"fr":{"word":"s'entendre avec","ipa":"[sɑ̃tɑ̃dʁ avɛk]","examples":[{"s":"Il s'entend bien avec ses collègues de bureau.","zh":"他和辦公室同事相處融洽。"},{"s":"Elle s'entend très bien avec ses voisins.","zh":"她和鄰居相處得非常好。"}]},"ja":{"word":"仲良くやっていく","kana":"なかよくやっていく","romaji":"nakayoku yatte iku","examples":[{"s":"新しい同僚とうまく仲良くやっていけそうです。","zh":"我似乎能和新同事好好相處。"},{"s":"彼女は義理の母と仲良くやっています。","zh":"她和婆婆相處得很好。"}]}}
]
