[
{"id":"p1991","de":{"word":"der Zaubertrank","ipa":"[ˈt͡saʊ̯bɐtʁaŋk]","examples":[{"s":"Die Hexe braute einen geheimnisvollen Zaubertrank in ihrem Kessel.","zh":"女巫在她的大鍋裡熬煮一種神祕的魔藥。"},{"s":"Im Märchen trinkt der Prinz einen Zaubertrank und wird geheilt.","zh":"在童話裡,王子喝下一瓶魔藥後便痊癒了。"}]},"fr":{"word":"la potion","ipa":"[pɔ.sjɔ̃]","examples":[{"s":"Le sorcier a préparé une potion magique pour guérir le malade.","zh":"巫師調製了一種魔藥來治好病人。"},{"s":"Elle a bu la potion et s'est aussitôt sentie mieux.","zh":"她喝下那瓶藥水,馬上就覺得好多了。"}]},"ja":{"word":"薬","kana":"くすり","romaji":"kusuri","examples":[{"s":"魔女は不思議な薬を大きな鍋で作っていた。","zh":"女巫用大鍋熬製著神祕的魔藥。"},{"s":"この薬を飲めば元気になると言われた。","zh":"據說喝下這藥水就會恢復精神。"}]}},
{"id":"p1992","de":{"word":"das Töpfchen","ipa":"[ˈtœpfçən]","examples":[{"s":"Unsere Tochter lernt gerade, aufs Töpfchen zu gehen.","zh":"我們的女兒正在學習使用便盆。"},{"s":"Das Töpfchen steht neben dem Bett des Kindes.","zh":"便盆放在孩子的床邊。"}]},"fr":{"word":"le pot","ipa":"[pɔ]","examples":[{"s":"Le petit garçon est enfin propre et utilise le pot tout seul.","zh":"這個小男孩終於學會自己用便盆了。"},{"s":"Elle a mis le pot dans la salle de bain pour le bébé.","zh":"她把便盆放在浴室裡給寶寶用。"}]},"ja":{"word":"おまる","kana":"おまる","romaji":"omaru","examples":[{"s":"子供がおまるでトイレの練習をしている。","zh":"孩子正用便盆練習上廁所。"},{"s":"おまるをリビングの隅に置いておいた。","zh":"我把便盆放在客廳的角落。"}]}},
{"id":"p1993","de":{"word":"der Beutel","ipa":"[ˈbɔɪ̯tl̩]","examples":[{"s":"Ich habe die Münzen in einen kleinen Beutel gesteckt.","zh":"我把硬幣裝進一個小袋子裡。"},{"s":"In seinem Beutel trug er Nüsse und getrocknete Früchte.","zh":"他的小袋子裡裝著堅果和果乾。"}]},"fr":{"word":"la pochette","ipa":"[pɔ.ʃɛt]","examples":[{"s":"Elle range ses pièces de monnaie dans une petite pochette.","zh":"她把零錢收在一個小零錢袋裡。"},{"s":"La pochette en cuir contient mes cartes et mes clés.","zh":"這個皮製小袋裝著我的卡片和鑰匙。"}]},"ja":{"word":"小袋","kana":"こぶくろ","romaji":"kobukuro","examples":[{"s":"小銭を小袋に入れて持ち歩いている。","zh":"我把零錢放在小袋子裡隨身帶著。"},{"s":"この小袋にアクセサリーをしまっておく。","zh":"我把飾品收進這個小袋子裡。"}]}},
{"id":"p1994","de":{"word":"das Geflügel","ipa":"[ɡəˈflyːɡl̩]","examples":[{"s":"Auf dem Bauernhof halten sie viel Geflügel wie Hühner und Enten.","zh":"農場裡養了很多家禽,像是雞和鴨。"},{"s":"Frisches Geflügel bekommt man am besten auf dem Wochenmarkt.","zh":"新鮮的家禽最好在週末市集買。"}]},"fr":{"word":"la volaille","ipa":"[vɔ.laj]","examples":[{"s":"Au marché, on trouve de la volaille fraîche tous les samedis.","zh":"每週六市場上都有新鮮的家禽。"},{"s":"Ma grand-mère élève de la volaille dans son jardin.","zh":"我奶奶在她的院子裡養家禽。"}]},"ja":{"word":"家禽","kana":"かきん","romaji":"kakin","examples":[{"s":"この農場では家禽を大切に育てている。","zh":"這座農場細心地飼養家禽。"},{"s":"鶏やアヒルなどの家禽を市場で売っている。","zh":"市場上販售雞、鴨等家禽。"}]}},
{"id":"p1995","de":{"word":"das Pfund","ipa":"[pfʊnt]","examples":[{"s":"Bitte geben Sie mir ein Pfund Tomaten.","zh":"請給我一磅番茄。"},{"s":"Das Paket wiegt fast fünf Pfund.","zh":"這個包裹將近五磅重。"}]},"fr":{"word":"la livre","ipa":"[livʁ]","examples":[{"s":"J'ai acheté une livre de pommes au marché.","zh":"我在市場買了一磅蘋果。"},{"s":"Ce sac de farine pèse deux livres.","zh":"這袋麵粉重兩磅。"}]},"ja":{"word":"ポンド","kana":"ポンド","romaji":"pondo","examples":[{"s":"りんごを一ポンド買ってきてください。","zh":"請買一磅蘋果回來。"},{"s":"この荷物は五ポンドほどの重さがある。","zh":"這件行李大約有五磅重。"}]}},
{"id":"p1996","de":{"word":"gießen","ipa":"[ˈɡiːsn̩]","examples":[{"s":"Kannst du mir bitte etwas Wasser ins Glas gießen?","zh":"可以請你倒一些水到杯子裡嗎?"},{"s":"Sie goss die Milch langsam in den Kaffee.","zh":"她慢慢地把牛奶倒進咖啡裡。"}]},"fr":{"word":"verser","ipa":"[vɛʁ.se]","examples":[{"s":"Peux-tu me verser un peu d'eau, s'il te plaît ?","zh":"可以請你幫我倒一點水嗎?"},{"s":"Elle a versé le vin dans les verres des invités.","zh":"她把酒倒進客人的杯子裡。"}]},"ja":{"word":"注ぐ","kana":"そそぐ","romaji":"sosogu","examples":[{"s":"コップに水を注いでくれますか。","zh":"可以幫我把水倒進杯子裡嗎?"},{"s":"彼女はカップにゆっくりとお茶を注いだ。","zh":"她慢慢地把茶倒進杯子裡。"}]}},
{"id":"p1997","de":{"word":"die Armut","ipa":"[ˈaːɐ̯muːt]","examples":[{"s":"Viele Familien in der Region leben in großer Armut.","zh":"這個地區有許多家庭生活在極度貧窮之中。"},{"s":"Die Regierung will die Armut in den Städten bekämpfen.","zh":"政府想要對抗城市裡的貧窮問題。"}]},"fr":{"word":"la pauvreté","ipa":"[po.vʁə.te]","examples":[{"s":"La pauvreté touche encore de nombreuses familles dans le monde.","zh":"貧窮至今仍影響著世界上許多家庭。"},{"s":"Cette association lutte contre la pauvreté depuis vingt ans.","zh":"這個組織對抗貧窮已經二十年了。"}]},"ja":{"word":"貧困","kana":"ひんこん","romaji":"hinkon","examples":[{"s":"世界にはまだ多くの人が貧困に苦しんでいる。","zh":"世界上仍有許多人為貧窮所苦。"},{"s":"政府は子供の貧困をなくそうと努力している。","zh":"政府正努力消除兒童的貧窮問題。"}]}},
{"id":"p1998","de":{"word":"das Pulver","ipa":"[ˈpʊlfɐ]","examples":[{"s":"Rühre das weiße Pulver in ein Glas warmes Wasser.","zh":"把這白色粉末攪進一杯溫水裡。"},{"s":"Das Waschmittel gibt es als Pulver oder als Flüssigkeit.","zh":"這款洗衣精有粉末狀和液狀兩種。"}]},"fr":{"word":"la poudre","ipa":"[pudʁ]","examples":[{"s":"Ajoute une cuillère de poudre de cacao dans le lait.","zh":"在牛奶裡加一匙可可粉。"},{"s":"Le médicament se présente sous forme de poudre.","zh":"這種藥是粉末狀的。"}]},"ja":{"word":"粉","kana":"こな","romaji":"kona","examples":[{"s":"白い粉をお湯によく溶かしてください。","zh":"請把白色粉末充分溶解在熱水裡。"},{"s":"この薬は粉になっているので飲みにくい。","zh":"這種藥是粉末狀的,所以不好吞。"}]}},
{"id":"p1999","de":{"word":"die Macht","ipa":"[maxt]","examples":[{"s":"Die Partei kam nach der Wahl an die Macht.","zh":"這個政黨在選舉後掌握了政權。"},{"s":"Niemand sollte zu viel Macht in einer Hand haben.","zh":"沒有人應該把過多的權力集中在一個人手中。"}]},"fr":{"word":"le pouvoir","ipa":"[pu.vwaʁ]","examples":[{"s":"Le nouveau gouvernement a pris le pouvoir le mois dernier.","zh":"新政府上個月掌握了政權。"},{"s":"Il aime le pouvoir et cherche toujours à commander.","zh":"他熱愛權力,總是想要發號施令。"}]},"ja":{"word":"権力","kana":"けんりょく","romaji":"kenryoku","examples":[{"s":"その政党は選挙で権力を握った。","zh":"那個政黨在選舉中掌握了政權。"},{"s":"一人に権力が集中するのは危険だ。","zh":"權力集中在一個人身上是危險的。"}]}},
{"id":"p2000","de":{"word":"die Powerbank","ipa":"[ˈpaʊ̯ɐbɛŋk]","examples":[{"s":"Ich habe unterwegs immer eine Powerbank dabei.","zh":"我出門在外總是隨身帶著行動電源。"},{"s":"Meine Powerbank ist leer, ich muss sie aufladen.","zh":"我的行動電源沒電了,得充一下。"}]},"fr":{"word":"la batterie externe","ipa":"[ba.tʁi ɛks.tɛʁn]","examples":[{"s":"J'emporte toujours une batterie externe quand je voyage.","zh":"我旅行時總會帶著行動電源。"},{"s":"Sa batterie externe peut recharger le téléphone trois fois.","zh":"他的行動電源可以幫手機充電三次。"}]},"ja":{"word":"モバイルバッテリー","kana":"モバイルバッテリー","romaji":"mobairu batterī","examples":[{"s":"外出するときは必ずモバイルバッテリーを持っていく。","zh":"外出時我一定會帶著行動電源。"},{"s":"モバイルバッテリーのおかげでスマホが切れずに済んだ。","zh":"多虧了行動電源,手機才沒有沒電。"}]}},
{"id":"p2001","de":{"word":"die Ein-Aus-Taste","ipa":"[ˈaɪ̯nˌʔaʊ̯sˌtastə]","examples":[{"s":"Drücke die Ein-Aus-Taste, um den Computer zu starten.","zh":"按下電源鍵來啟動電腦。"},{"s":"Die Ein-Aus-Taste befindet sich an der Seite des Geräts.","zh":"電源鍵位於裝置的側邊。"}]},"fr":{"word":"le bouton d'alimentation","ipa":"[bu.tɔ̃ da.li.mɑ̃.ta.sjɔ̃]","examples":[{"s":"Appuie sur le bouton d'alimentation pour allumer l'écran.","zh":"按下電源鍵來開啟螢幕。"},{"s":"Le bouton d'alimentation se trouve en haut du téléphone.","zh":"電源鍵位在手機的上方。"}]},"ja":{"word":"電源ボタン","kana":"でんげんボタン","romaji":"dengen botan","examples":[{"s":"電源ボタンを長押しすると再起動できる。","zh":"長按電源鍵就可以重新啟動。"},{"s":"電源ボタンは本体の右側にあります。","zh":"電源鍵在機身的右側。"}]}},
{"id":"p2002","de":{"word":"der Stromausfall","ipa":"[ˈʃtʁoːmʔaʊ̯sˌfal]","examples":[{"s":"Gestern Abend gab es einen langen Stromausfall im ganzen Viertel.","zh":"昨晚整個社區停電了很久。"},{"s":"Wegen des Sturms kam es zu einem Stromausfall.","zh":"因為暴風雨的關係發生了停電。"}]},"fr":{"word":"la coupure de courant","ipa":"[ku.pyʁ də ku.ʁɑ̃]","examples":[{"s":"Il y a eu une coupure de courant pendant tout l'après-midi.","zh":"整個下午都停電了。"},{"s":"La tempête a provoqué une coupure de courant dans le quartier.","zh":"暴風雨造成了社區停電。"}]},"ja":{"word":"停電","kana":"ていでん","romaji":"teiden","examples":[{"s":"台風の影響で昨夜は長い停電があった。","zh":"因為颱風的影響,昨晚停電了很久。"},{"s":"停電のときのために懐中電灯を用意している。","zh":"為了停電時做準備,我備了手電筒。"}]}},
{"id":"p2003","de":{"word":"das Kraftwerk","ipa":"[ˈkʁaftvɛʁk]","examples":[{"s":"Das neue Kraftwerk versorgt die ganze Stadt mit Strom.","zh":"這座新發電廠供應整座城市的電力。"},{"s":"In der Nähe des Flusses wird ein Kraftwerk gebaut.","zh":"河邊正在興建一座發電廠。"}]},"fr":{"word":"la centrale électrique","ipa":"[sɑ̃.tʁal e.lɛk.tʁik]","examples":[{"s":"La centrale électrique fournit de l'énergie à toute la région.","zh":"這座發電廠供應整個地區的電力。"},{"s":"Ils construisent une nouvelle centrale électrique près de la côte.","zh":"他們正在海岸附近興建一座新發電廠。"}]},"ja":{"word":"発電所","kana":"はつでんしょ","romaji":"hatsudensho","examples":[{"s":"この発電所は町全体に電気を送っている。","zh":"這座發電廠供電給整個城鎮。"},{"s":"川の近くに大きな発電所が建てられた。","zh":"河邊建了一座大型發電廠。"}]}},
{"id":"p2004","de":{"word":"die Übung","ipa":"[ˈyːbʊŋ]","examples":[{"s":"Mit täglicher Übung wirst du schnell besser.","zh":"每天練習你就會進步得很快。"},{"s":"Vor dem Konzert brauche ich noch viel Übung.","zh":"演出前我還需要很多練習。"}]},"fr":{"word":"la pratique","ipa":"[pʁa.tik]","examples":[{"s":"C'est avec la pratique que l'on progresse au piano.","zh":"透過練習才能在鋼琴上進步。"},{"s":"Elle fait de la pratique tous les jours pour l'examen.","zh":"她每天為了考試做練習。"}]},"ja":{"word":"練習","kana":"れんしゅう","romaji":"renshū","examples":[{"s":"毎日の練習でだんだん上手になってきた。","zh":"透過每天的練習,我漸漸變得熟練了。"},{"s":"試合の前にもっと練習が必要だ。","zh":"比賽前還需要更多練習。"}]}},
{"id":"p2005","de":{"word":"beten","ipa":"[ˈbeːtn̩]","examples":[{"s":"Jeden Abend beten sie gemeinsam vor dem Schlafengehen.","zh":"每天晚上他們睡前會一起祈禱。"},{"s":"Sie ging in die Kirche, um für ihre Familie zu beten.","zh":"她去教堂為她的家人祈禱。"}]},"fr":{"word":"prier","ipa":"[pʁi.je]","examples":[{"s":"Chaque matin, elle prie avant de commencer sa journée.","zh":"每天早上她在開始一天之前都會祈禱。"},{"s":"Ils sont allés à l'église pour prier ensemble.","zh":"他們去教堂一起祈禱。"}]},"ja":{"word":"祈る","kana":"いのる","romaji":"inoru","examples":[{"s":"彼女は家族の健康を毎晩祈っている。","zh":"她每晚都為家人的健康祈禱。"},{"s":"神社で合格できるように祈った。","zh":"我在神社祈禱能夠考上。"}]}},
{"id":"p2006","de":{"word":"die Gebetskette","ipa":"[ɡəˈbeːtsˌkɛtə]","examples":[{"s":"Der alte Mönch hielt eine Gebetskette in seinen Händen.","zh":"這位老僧手中拿著一串念珠。"},{"s":"Sie schenkte mir eine Gebetskette aus Holzperlen.","zh":"她送了我一串木珠念珠。"}]},"fr":{"word":"le chapelet","ipa":"[ʃa.plɛ]","examples":[{"s":"La vieille dame récite ses prières avec un chapelet.","zh":"這位老太太拿著念珠念禱文。"},{"s":"Il porte toujours un chapelet autour du poignet.","zh":"他總是把一串念珠戴在手腕上。"}]},"ja":{"word":"数珠","kana":"じゅず","romaji":"juzu","examples":[{"s":"お坊さんは手に数珠を持ってお経を唱えた。","zh":"僧人手持念珠誦經。"},{"s":"祖母はお参りのときいつも数珠を持っていく。","zh":"祖母參拜時總是帶著念珠。"}]}},
{"id":"p2007","de":{"word":"das Gebet","ipa":"[ɡəˈbeːt]","examples":[{"s":"Vor dem Essen sprachen sie ein kurzes Gebet.","zh":"用餐前他們念了一段簡短的禱告。"},{"s":"Sein Gebet gab ihm in der schweren Zeit Trost.","zh":"在艱難的時期,禱告給了他慰藉。"}]},"fr":{"word":"la prière","ipa":"[pʁi.jɛʁ]","examples":[{"s":"Avant le repas, la famille dit une courte prière.","zh":"用餐前,全家人念一段簡短的禱告。"},{"s":"Elle trouve du réconfort dans la prière chaque soir.","zh":"她每晚在禱告中找到慰藉。"}]},"ja":{"word":"祈り","kana":"いのり","romaji":"inori","examples":[{"s":"食事の前に短い祈りを捧げた。","zh":"用餐前獻上一段簡短的禱告。"},{"s":"つらいとき、祈りが彼の心を支えた。","zh":"在艱難時,禱告支撐著他的心。"}]}},
{"id":"p2008","de":{"word":"vorhersagen","ipa":"[foːɐ̯ˈheːɐ̯ˌzaːɡn̩]","examples":[{"s":"Die Experten können das Wetter nur wenige Tage vorhersagen.","zh":"專家只能預測未來幾天的天氣。"},{"s":"Niemand konnte vorhersagen, wie das Spiel enden würde.","zh":"沒有人能預測這場比賽會如何結束。"}]},"fr":{"word":"prédire","ipa":"[pʁe.diʁ]","examples":[{"s":"Les scientifiques essaient de prédire les tremblements de terre.","zh":"科學家試圖預測地震。"},{"s":"Personne ne pouvait prédire le résultat de l'élection.","zh":"沒有人能預測選舉的結果。"}]},"ja":{"word":"予測する","kana":"よそくする","romaji":"yosoku suru","examples":[{"s":"専門家は明日の天気を予測した。","zh":"專家預測了明天的天氣。"},{"s":"試合の結果を予測するのは難しい。","zh":"要預測比賽的結果很困難。"}]}},
{"id":"p2009","de":{"word":"schwanger","ipa":"[ˈʃvaŋɐ]","examples":[{"s":"Meine Schwester ist im fünften Monat schwanger.","zh":"我姊姊懷孕五個月了。"},{"s":"Als sie schwanger war, achtete sie sehr auf ihre Ernährung.","zh":"她懷孕時非常注意自己的飲食。"}]},"fr":{"word":"enceinte","ipa":"[ɑ̃.sɛ̃t]","examples":[{"s":"Ma sœur est enceinte de son premier enfant.","zh":"我姊姊懷了她的第一個孩子。"},{"s":"Elle est enceinte de six mois et se sent bien.","zh":"她懷孕六個月了,感覺很好。"}]},"ja":{"word":"妊娠している","kana":"にんしんしている","romaji":"ninshin shite iru","examples":[{"s":"姉は今、妊娠していてとても嬉しそうだ。","zh":"我姊姊現在懷孕了,看起來很開心。"},{"s":"妊娠しているので、無理をしないようにしている。","zh":"因為懷孕了,我盡量不勉強自己。"}]}},
{"id":"p2010","de":{"word":"vorheizen","ipa":"[ˈfoːɐ̯ˌhaɪ̯t͡sn̩]","examples":[{"s":"Bitte den Ofen auf 180 Grad vorheizen.","zh":"請把烤箱預熱到一百八十度。"},{"s":"Ich habe vergessen, den Backofen vorzuheizen.","zh":"我忘了把烤箱預熱。"}]},"fr":{"word":"préchauffer","ipa":"[pʁe.ʃo.fe]","examples":[{"s":"Il faut préchauffer le four à deux cents degrés.","zh":"要把烤箱預熱到兩百度。"},{"s":"N'oublie pas de préchauffer le four avant de mettre le gâteau.","zh":"放蛋糕前別忘了把烤箱預熱。"}]},"ja":{"word":"予熱する","kana":"よねつする","romaji":"yonetsu suru","examples":[{"s":"オーブンを百八十度に予熱してください。","zh":"請把烤箱預熱到一百八十度。"},{"s":"パンを焼く前にオーブンを予熱しておく。","zh":"烤麵包前先把烤箱預熱好。"}]}},
{"id":"p2011","de":{"word":"vorgeschichtlich","ipa":"[ˈfoːɐ̯ɡəˌʃɪçtlɪç]","examples":[{"s":"In der Höhle fand man vorgeschichtliche Malereien.","zh":"人們在洞穴裡發現了史前的壁畫。"},{"s":"Das Museum zeigt Werkzeuge aus vorgeschichtlicher Zeit.","zh":"這間博物館展出史前時期的工具。"}]},"fr":{"word":"préhistorique","ipa":"[pʁe.is.tɔ.ʁik]","examples":[{"s":"Ces peintures préhistoriques ont des milliers d'années.","zh":"這些史前壁畫有數千年的歷史。"},{"s":"On a découvert des outils préhistoriques dans la grotte.","zh":"人們在洞穴裡發現了史前的工具。"}]},"ja":{"word":"先史時代の","kana":"せんしじだいの","romaji":"senshi jidai no","examples":[{"s":"洞窟で先史時代の壁画が見つかった。","zh":"在洞穴裡發現了史前時代的壁畫。"},{"s":"博物館には先史時代の道具が展示されている。","zh":"博物館裡展示著史前時代的工具。"}]}},
{"id":"p2012","de":{"word":"die Premiere","ipa":"[pʁəˈmi̯eːʁə]","examples":[{"s":"Die Premiere des neuen Films war ein großer Erfolg.","zh":"這部新電影的首映非常成功。"},{"s":"Viele Stars kamen zur Premiere des Theaterstücks.","zh":"許多明星出席了這齣戲劇的首映。"}]},"fr":{"word":"la première","ipa":"[la pʁə.mjɛʁ]","examples":[{"s":"La première du film a eu lieu hier soir à Paris.","zh":"這部電影的首映昨晚在巴黎舉行。"},{"s":"Nous avons été invités à la première de la pièce.","zh":"我們受邀參加這齣戲的首映。"}]},"ja":{"word":"初演","kana":"しょえん","romaji":"shoen","examples":[{"s":"新作映画の初演には多くのファンが集まった。","zh":"新片的首映吸引了許多影迷聚集。"},{"s":"その舞台の初演は大成功だった。","zh":"那齣舞台劇的首演非常成功。"}]}},
{"id":"p2013","de":{"word":"die Prämisse","ipa":"[pʁɛˈmɪsə]","examples":[{"s":"Seine Argumentation beruht auf einer falschen Prämisse.","zh":"他的論證建立在一個錯誤的前提上。"},{"s":"Wir müssen zuerst die Prämisse dieser Theorie prüfen.","zh":"我們必須先檢驗這個理論的前提。"}]},"fr":{"word":"la prémisse","ipa":"[pʁe.mis]","examples":[{"s":"Tout son raisonnement repose sur une prémisse discutable.","zh":"他整個推論建立在一個有爭議的前提上。"},{"s":"Si la prémisse est fausse, la conclusion l'est aussi.","zh":"如果前提是錯的,結論也會是錯的。"}]},"ja":{"word":"前提","kana":"ぜんてい","romaji":"zentei","examples":[{"s":"その主張は間違った前提に基づいている。","zh":"那個主張建立在錯誤的前提上。"},{"s":"議論を始める前に前提を確認しよう。","zh":"開始討論前先確認一下前提吧。"}]}},
{"id":"p2014","de":{"word":"vorbereiten","ipa":"[ˈfoːɐ̯bəˌʁaɪ̯tn̩]","examples":[{"s":"Ich muss noch das Abendessen für die Gäste vorbereiten.","zh":"我還得為客人準備晚餐。"},{"s":"Sie bereitet sich seit Wochen auf die Prüfung vor.","zh":"她為了考試已經準備好幾週了。"}]},"fr":{"word":"préparer","ipa":"[pʁe.pa.ʁe]","examples":[{"s":"Je dois préparer le dîner avant l'arrivée des invités.","zh":"我得在客人來之前準備好晚餐。"},{"s":"Elle prépare son examen depuis plusieurs semaines.","zh":"她為考試已經準備了好幾週。"}]},"ja":{"word":"準備する","kana":"じゅんびする","romaji":"junbi suru","examples":[{"s":"お客さんのために夕食を準備している。","zh":"我正在為客人準備晚餐。"},{"s":"試験に向けて何週間も準備している。","zh":"為了考試我已經準備了好幾週。"}]}},
{"id":"p2015","de":{"word":"das Rezept","ipa":"[ʁeˈt͡sɛpt]","examples":[{"s":"Der Arzt hat mir ein Rezept für die Tabletten gegeben.","zh":"醫生開了一張藥的處方箋給我。"},{"s":"Ohne Rezept bekommt man dieses Medikament nicht.","zh":"沒有處方箋就拿不到這種藥。"}]},"fr":{"word":"l'ordonnance","ipa":"[l‿ɔʁ.dɔ.nɑ̃s]","examples":[{"s":"Le médecin m'a fait une ordonnance pour mes médicaments.","zh":"醫生為我的藥開了一張處方箋。"},{"s":"On ne peut pas acheter ce médicament sans ordonnance.","zh":"沒有處方箋就買不到這種藥。"}]},"ja":{"word":"処方箋","kana":"しょほうせん","romaji":"shohōsen","examples":[{"s":"医者は薬の処方箋を書いてくれた。","zh":"醫生幫我開了藥的處方箋。"},{"s":"この薬は処方箋がないと買えません。","zh":"這種藥沒有處方箋就買不到。"}]}},
{"id":"p2016","de":{"word":"das Geschenk","ipa":"[ɡəˈʃɛŋk]","examples":[{"s":"Ich habe ein kleines Geschenk für deinen Geburtstag.","zh":"我為你的生日準備了一個小禮物。"},{"s":"Sie packte das Geschenk in buntes Papier ein.","zh":"她把禮物用彩色的紙包了起來。"}]},"fr":{"word":"le cadeau","ipa":"[ka.do]","examples":[{"s":"J'ai acheté un cadeau pour l'anniversaire de ma mère.","zh":"我為媽媽的生日買了一份禮物。"},{"s":"Il a ouvert son cadeau avec beaucoup de joie.","zh":"他非常開心地拆開了他的禮物。"}]},"ja":{"word":"プレゼント","kana":"プレゼント","romaji":"purezento","examples":[{"s":"友達の誕生日にプレゼントを買った。","zh":"我為朋友的生日買了禮物。"},{"s":"彼女はプレゼントをきれいな紙で包んだ。","zh":"她用漂亮的紙把禮物包了起來。"}]}},
{"id":"p2017","de":{"word":"die Präsentation","ipa":"[pʁɛzɛntaˈt͡si̯oːn]","examples":[{"s":"Morgen halte ich eine Präsentation vor dem ganzen Team.","zh":"明天我要在整個團隊面前做簡報。"},{"s":"Ihre Präsentation war klar und gut vorbereitet.","zh":"她的簡報清楚且準備充分。"}]},"fr":{"word":"la présentation","ipa":"[pʁe.zɑ̃.ta.sjɔ̃]","examples":[{"s":"Je dois faire une présentation devant mes collègues demain.","zh":"我明天得在同事面前做簡報。"},{"s":"Sa présentation a impressionné tout le monde.","zh":"她的簡報讓所有人都印象深刻。"}]},"ja":{"word":"プレゼンテーション","kana":"プレゼンテーション","romaji":"purezentēshon","examples":[{"s":"明日、チームの前でプレゼンテーションをする。","zh":"明天我要在團隊面前做簡報。"},{"s":"彼のプレゼンテーションはとても分かりやすかった。","zh":"他的簡報非常淺顯易懂。"}]}},
{"id":"p2018","de":{"word":"der Präsident","ipa":"[pʁɛziˈdɛnt]","examples":[{"s":"Der Präsident hielt eine Rede vor dem Parlament.","zh":"總統在國會前發表了演說。"},{"s":"Der neue Präsident wurde gestern gewählt.","zh":"新總統昨天當選了。"}]},"fr":{"word":"le président","ipa":"[pʁe.zi.dɑ̃]","examples":[{"s":"Le président a prononcé un discours important hier.","zh":"總統昨天發表了一場重要的演說。"},{"s":"Les citoyens ont élu un nouveau président.","zh":"公民們選出了一位新總統。"}]},"ja":{"word":"大統領","kana":"だいとうりょう","romaji":"daitōryō","examples":[{"s":"大統領は議会で演説を行った。","zh":"總統在議會發表了演說。"},{"s":"新しい大統領が昨日選ばれた。","zh":"新總統昨天當選了。"}]}},
{"id":"p2019","de":{"word":"der Druck","ipa":"[dʁʊk]","examples":[{"s":"Bei der Arbeit stehe ich zurzeit unter großem Druck.","zh":"我現在工作上承受著很大的壓力。"},{"s":"Der Druck vor der Prüfung war kaum auszuhalten.","zh":"考試前的壓力幾乎讓人受不了。"}]},"fr":{"word":"la pression","ipa":"[pʁɛ.sjɔ̃]","examples":[{"s":"Il ressent beaucoup de pression au travail en ce moment.","zh":"他現在在工作上感受到很大的壓力。"},{"s":"La pression des examens la rend nerveuse.","zh":"考試的壓力讓她很緊張。"}]},"ja":{"word":"プレッシャー","kana":"プレッシャー","romaji":"puresshā","examples":[{"s":"最近、仕事のプレッシャーで眠れない。","zh":"最近因為工作的壓力而睡不著。"},{"s":"試験のプレッシャーに負けないようにしている。","zh":"我努力不被考試的壓力打倒。"}]}},
{"id":"p2020","de":{"word":"die Vorschau","ipa":"[ˈfoːɐ̯ˌʃaʊ̯]","examples":[{"s":"In der Vorschau kannst du sehen, wie das Dokument aussehen wird.","zh":"在預覽中你可以看到文件會長什麼樣子。"},{"s":"Vor dem Drucken werfe ich immer einen Blick in die Vorschau.","zh":"列印前我總會看一下預覽。"}]},"fr":{"word":"l'aperçu","ipa":"[l‿a.pɛʁ.sy]","examples":[{"s":"L'aperçu te montre le document avant l'impression.","zh":"預覽會在列印前讓你看到文件。"},{"s":"Regarde l'aperçu pour vérifier la mise en page.","zh":"看一下預覽,確認一下版面。"}]},"ja":{"word":"プレビュー","kana":"プレビュー","romaji":"purebyū","examples":[{"s":"印刷する前にプレビューで確認しよう。","zh":"列印前先用預覽確認一下吧。"},{"s":"プレビューで文書の見た目をチェックできる。","zh":"可以用預覽檢查文件的外觀。"}]}}
]
