[
{"id":"p0191","de":{"word":"das Schnäppchen","ipa":"[ˈʃnɛpçən]","examples":[{"s":"Diese Jacke war ein echtes Schnäppchen.","zh":"這件外套真是划算的東西。"},{"s":"Auf dem Flohmarkt kann man gut über den Preis handeln.","zh":"在跳蚤市場可以好好討價還價。"}]},"fr":{"word":"la bonne affaire","ipa":"[la bɔn afɛʁ]","examples":[{"s":"J'ai fait une bonne affaire pendant les soldes.","zh":"我在打折時買到了划算的東西。"},{"s":"Au marché, il faut savoir marchander.","zh":"在市場上要懂得討價還價。"}]},"ja":{"word":"掘り出し物","kana":"ほりだしもの","romaji":"horidashimono","examples":[{"s":"このコートは掘り出し物だったよ。","zh":"這件大衣真是划算的東西。"},{"s":"市場で値段を交渉した。","zh":"我在市場討價還價。"}]}},
{"id":"p0192","de":{"word":"der Barista","ipa":"[baˈʁista]","examples":[{"s":"Der Barista macht einen wunderbaren Cappuccino.","zh":"這位咖啡師做的卡布奇諾很棒。"},{"s":"Sie arbeitet als Barista in einem kleinen Café.","zh":"她在一家小咖啡館當咖啡師。"}]},"fr":{"word":"le barista","ipa":"[lə baʁista]","examples":[{"s":"Le barista prépare un café délicieux.","zh":"這位咖啡師沖了一杯美味的咖啡。"},{"s":"Ce barista connaît bien son métier.","zh":"這位咖啡師很懂他的手藝。"}]},"ja":{"word":"バリスタ","kana":"バリスタ","romaji":"barisuta","examples":[{"s":"あのバリスタのラテはとても美味しい。","zh":"那位咖啡師的拿鐵很好喝。"},{"s":"彼はカフェでバリスタとして働いている。","zh":"他在咖啡館當咖啡師。"}]}},
{"id":"p0193","de":{"word":"bellen","ipa":"[ˈbɛlən]","examples":[{"s":"Der Hund bellt die ganze Nacht.","zh":"這隻狗整晚都在吠叫。"},{"s":"Warum bellt dein Hund so laut?","zh":"你的狗為什麼叫得這麼大聲？"}]},"fr":{"word":"aboyer","ipa":"[abwaje]","examples":[{"s":"Le chien aboie contre le facteur.","zh":"這隻狗對著郵差吠叫。"},{"s":"Mon chien aboie quand quelqu'un sonne.","zh":"有人按鈴時我的狗會吠叫。"}]},"ja":{"word":"吠える","kana":"ほえる","romaji":"hoeru","examples":[{"s":"犬が知らない人に吠えている。","zh":"狗對著陌生人吠叫。"},{"s":"夜中に犬が吠えて目が覚めた。","zh":"半夜狗吠把我吵醒了。"}]}},
{"id":"p0194","de":{"word":"die Scheune","ipa":"[ˈʃɔɪ̯nə]","examples":[{"s":"Das Heu wird in der Scheune gelagert.","zh":"乾草儲存在穀倉裡。"},{"s":"Die alte Scheune steht hinter dem Bauernhof.","zh":"那座舊穀倉在農場後面。"}]},"fr":{"word":"la grange","ipa":"[la ɡʁɑ̃ʒ]","examples":[{"s":"Les animaux dorment dans la grange.","zh":"動物們睡在畜舍裡。"},{"s":"On stocke le foin dans la grange.","zh":"我們把乾草存放在穀倉裡。"}]},"ja":{"word":"納屋","kana":"なや","romaji":"naya","examples":[{"s":"干し草を納屋に積んだ。","zh":"我把乾草堆進穀倉裡。"},{"s":"納屋の中に牛が入っている。","zh":"牛在畜舍裡面。"}]}},
{"id":"p0195","de":{"word":"die Seepocke","ipa":"[ˈzeːˌpɔkə]","examples":[{"s":"Der Schiffsrumpf ist voller Seepocken.","zh":"船身上滿是藤壺。"},{"s":"Seepocken haften fest an den Felsen.","zh":"藤壺牢牢附著在岩石上。"}]},"fr":{"word":"la bernacle","ipa":"[la bɛʁnakl]","examples":[{"s":"Des bernacles couvrent la coque du bateau.","zh":"藤壺覆蓋在船殼上。"},{"s":"Les bernacles s'accrochent aux rochers.","zh":"藤壺附著在岩石上。"}]},"ja":{"word":"フジツボ","kana":"フジツボ","romaji":"fujitsubo","examples":[{"s":"船底にフジツボがびっしり付いている。","zh":"船底密密麻麻長滿藤壺。"},{"s":"岩にフジツボがついていた。","zh":"岩石上長著藤壺。"}]}},
{"id":"p0196","de":{"word":"der Bauernhof","ipa":"[ˈbaʊ̯ɐnˌhoːf]","examples":[{"s":"Die Hühner laufen frei auf dem Bauernhof herum.","zh":"雞在農家庭院裡自由走動。"},{"s":"Im Hof des Bauernhofs steht ein Traktor.","zh":"農家庭院裡停著一台拖拉機。"}]},"fr":{"word":"la basse-cour","ipa":"[la bas kuʁ]","examples":[{"s":"Les poules picorent dans la basse-cour.","zh":"母雞在畜欄場裡啄食。"},{"s":"La basse-cour est pleine de canards.","zh":"農家庭院裡滿是鴨子。"}]},"ja":{"word":"農家の庭","kana":"のうかのにわ","romaji":"nōka no niwa","examples":[{"s":"農家の庭で鶏が餌をついばんでいる。","zh":"雞在農家庭院裡啄食。"},{"s":"農家の庭にアヒルが集まっている。","zh":"鴨子聚集在農家庭院裡。"}]}},
{"id":"p0197","de":{"word":"die Kaserne","ipa":"[kaˈzɛʁnə]","examples":[{"s":"Die Soldaten schlafen in der Kaserne.","zh":"士兵們睡在營房裡。"},{"s":"Die Kaserne liegt am Rand der Stadt.","zh":"兵營位於城鎮邊緣。"}]},"fr":{"word":"la caserne","ipa":"[la kazɛʁn]","examples":[{"s":"Les soldats vivent dans la caserne.","zh":"士兵們住在營房裡。"},{"s":"La caserne se trouve près de la gare.","zh":"兵營在火車站附近。"}]},"ja":{"word":"兵舎","kana":"へいしゃ","romaji":"heisha","examples":[{"s":"兵士たちは兵舎で寝起きしている。","zh":"士兵們在營房裡起居。"},{"s":"兵舎は町のはずれにある。","zh":"兵營位於城鎮邊緣。"}]}},
{"id":"p0198","de":{"word":"die Basis","ipa":"[ˈbaːzɪs]","examples":[{"s":"Die Truppen kehrten zur Basis zurück.","zh":"部隊回到了基地。"},{"s":"Die Militärbasis ist streng bewacht.","zh":"這座軍事基地戒備森嚴。"}]},"fr":{"word":"la base","ipa":"[la baz]","examples":[{"s":"Les soldats sont rentrés à la base.","zh":"士兵們回到了基地。"},{"s":"La base militaire est très surveillée.","zh":"這座軍事基地戒備森嚴。"}]},"ja":{"word":"基地","kana":"きち","romaji":"kichi","examples":[{"s":"部隊は基地に戻った。","zh":"部隊回到了基地。"},{"s":"軍の基地は厳重に守られている。","zh":"軍事基地戒備森嚴。"}]}},
{"id":"p0199","de":{"word":"der Keller","ipa":"[ˈkɛlɐ]","examples":[{"s":"Wir lagern den Wein im Keller.","zh":"我們把酒儲藏在地下室。"},{"s":"Im Keller ist es kühl und dunkel.","zh":"地下室又涼又暗。"}]},"fr":{"word":"le sous-sol","ipa":"[lə su sɔl]","examples":[{"s":"La machine à laver est au sous-sol.","zh":"洗衣機在地下室。"},{"s":"On range les vieux cartons au sous-sol.","zh":"我們把舊紙箱收在地下室。"}]},"ja":{"word":"地下室","kana":"ちかしつ","romaji":"chikashitsu","examples":[{"s":"ワインを地下室に保管している。","zh":"我把酒儲藏在地下室。"},{"s":"地下室はひんやりとして暗い。","zh":"地下室又涼又暗。"}]}},
{"id":"p0200","de":{"word":"der Basketball","ipa":"[ˈbaːskɛtˌbal]","examples":[{"s":"Am Wochenende spielen wir Basketball im Park.","zh":"週末我們在公園打籃球。"},{"s":"Er ist im Basketball richtig gut.","zh":"他籃球打得很好。"}]},"fr":{"word":"le basket-ball","ipa":"[lə basket bol]","examples":[{"s":"Nous jouons au basket-ball après l'école.","zh":"放學後我們打籃球。"},{"s":"Le basket-ball est son sport préféré.","zh":"籃球是他最喜歡的運動。"}]},"ja":{"word":"バスケットボール","kana":"バスケットボール","romaji":"basukettobōru","examples":[{"s":"週末に公園でバスケットボールをする。","zh":"週末我在公園打籃球。"},{"s":"彼はバスケットボールが得意だ。","zh":"他很擅長打籃球。"}]}},
{"id":"p0201","de":{"word":"baden","ipa":"[ˈbaːdn̩]","examples":[{"s":"Die Mutter badet ihr Baby jeden Abend.","zh":"媽媽每晚幫寶寶洗澡。"},{"s":"Wir baden den Hund im Garten.","zh":"我們在花園幫狗洗澡。"}]},"fr":{"word":"baigner","ipa":"[beɲe]","examples":[{"s":"Elle baigne le bébé dans la petite baignoire.","zh":"她在小浴盆裡幫寶寶洗澡。"},{"s":"Nous baignons le chien après la promenade.","zh":"散步後我們幫狗洗澡。"}]},"ja":{"word":"入浴させる","kana":"にゅうよくさせる","romaji":"nyūyoku saseru","examples":[{"s":"母は毎晩赤ちゃんを入浴させる。","zh":"媽媽每晚幫寶寶洗澡。"},{"s":"庭で犬を洗ってあげた。","zh":"我在花園幫狗洗澡。"}]}},
{"id":"p0202","de":{"word":"das Badezimmer","ipa":"[ˈbaːdəˌt͡sɪmɐ]","examples":[{"s":"Das Badezimmer ist gerade besetzt.","zh":"浴室現在有人在用。"},{"s":"Wir renovieren nächste Woche unser Badezimmer.","zh":"下週我們要翻修浴室。"}]},"fr":{"word":"la salle de bain","ipa":"[la sal də bɛ̃]","examples":[{"s":"La salle de bain est au bout du couloir.","zh":"浴室在走廊盡頭。"},{"s":"Il y a une baignoire dans la salle de bain.","zh":"浴室裡有一個浴缸。"}]},"ja":{"word":"浴室","kana":"よくしつ","romaji":"yokushitsu","examples":[{"s":"浴室は今使われている。","zh":"浴室現在有人在用。"},{"s":"来週、浴室をリフォームする。","zh":"下週我們要翻修浴室。"}]}},
{"id":"p0203","de":{"word":"der Teig","ipa":"[taɪ̯k]","examples":[{"s":"Rühre den Teig gut, bevor du ihn in die Pfanne gibst.","zh":"把麵糊攪勻後再倒進鍋裡。"},{"s":"Der Teig für die Pfannkuchen ist zu dick.","zh":"做鬆餅的麵糊太稠了。"}]},"fr":{"word":"la pâte","ipa":"[la pat]","examples":[{"s":"Verse la pâte à crêpes dans la poêle.","zh":"把可麗餅麵糊倒進平底鍋。"},{"s":"La pâte est trop liquide, ajoute de la farine.","zh":"麵糊太稀了，加點麵粉。"}]},"ja":{"word":"生地","kana":"きじ","romaji":"kiji","examples":[{"s":"パンケーキの生地をよく混ぜる。","zh":"把鬆餅麵糊攪拌均勻。"},{"s":"生地をフライパンに流し込んだ。","zh":"我把麵糊倒進平底鍋。"}]}},
{"id":"p0204","de":{"word":"die Batterie","ipa":"[batəˈʁiː]","examples":[{"s":"Die Batterie meines Handys ist leer.","zh":"我手機的電池沒電了。"},{"s":"Ich muss neue Batterien für die Fernbedienung kaufen.","zh":"我得買新電池給遙控器。"}]},"fr":{"word":"la batterie","ipa":"[la batʁi]","examples":[{"s":"La batterie de mon téléphone est déchargée.","zh":"我手機的電池沒電了。"},{"s":"Il faut changer la batterie de la voiture.","zh":"得換車子的電池了。"}]},"ja":{"word":"電池","kana":"でんち","romaji":"denchi","examples":[{"s":"スマホの電池が切れてしまった。","zh":"我手機的電池沒電了。"},{"s":"リモコンの電池を交換した。","zh":"我換了遙控器的電池。"}]}},
{"id":"p0205","de":{"word":"die Schlacht","ipa":"[ʃlaxt]","examples":[{"s":"Die Schlacht dauerte drei Tage.","zh":"這場戰役持續了三天。"},{"s":"Viele Soldaten fielen in der Schlacht.","zh":"許多士兵在這場戰鬥中陣亡。"}]},"fr":{"word":"la bataille","ipa":"[la bataj]","examples":[{"s":"La bataille a duré toute la nuit.","zh":"這場戰役持續了一整夜。"},{"s":"Ils ont gagné la bataille difficilement.","zh":"他們艱難地贏得了這場戰鬥。"}]},"ja":{"word":"戦い","kana":"たたかい","romaji":"tatakai","examples":[{"s":"その戦いは三日間続いた。","zh":"這場戰役持續了三天。"},{"s":"多くの兵士がその戦いで命を落とした。","zh":"許多士兵在這場戰鬥中喪命。"}]}},
{"id":"p0206","de":{"word":"die Bucht","ipa":"[bʊxt]","examples":[{"s":"Die Boote liegen ruhig in der Bucht.","zh":"船隻靜靜地停在海灣裡。"},{"s":"Wir haben in einer kleinen Bucht gebadet.","zh":"我們在一個小海灣裡游泳。"}]},"fr":{"word":"la baie","ipa":"[la bɛ]","examples":[{"s":"Les bateaux se reposent dans la baie.","zh":"船隻停泊在海灣裡。"},{"s":"La baie est calme au coucher du soleil.","zh":"日落時海灣很平靜。"}]},"ja":{"word":"湾","kana":"わん","romaji":"wan","examples":[{"s":"船が静かに湾に浮かんでいる。","zh":"船隻靜靜地停在海灣裡。"},{"s":"小さな湾で泳いだ。","zh":"我們在一個小海灣裡游泳。"}]}},
{"id":"p0207","de":{"word":"der Strand","ipa":"[ʃtʁant]","examples":[{"s":"Im Sommer gehen wir oft an den Strand.","zh":"夏天我們常去海灘。"},{"s":"Die Kinder bauen Sandburgen am Strand.","zh":"孩子們在沙灘上堆沙堡。"}]},"fr":{"word":"la plage","ipa":"[la plaʒ]","examples":[{"s":"Nous passons la journée à la plage.","zh":"我們在海灘上待了一整天。"},{"s":"Les enfants jouent dans le sable sur la plage.","zh":"孩子們在沙灘上玩沙。"}]},"ja":{"word":"海辺","kana":"うみべ","romaji":"umibe","examples":[{"s":"夏はよく海辺へ行く。","zh":"夏天我們常去海灘。"},{"s":"子どもたちが砂浜で砂の城を作っている。","zh":"孩子們在沙灘上堆沙堡。"}]}},
{"id":"p0208","de":{"word":"die Perlen","ipa":"[ˈpɛʁlən]","examples":[{"s":"Sie fädelt bunte Perlen auf eine Schnur.","zh":"她把彩色珠子串在線上。"},{"s":"Die Kette besteht aus kleinen Perlen.","zh":"這條項鍊是用小珠子做的。"}]},"fr":{"word":"les perles","ipa":"[le pɛʁl]","examples":[{"s":"Elle enfile des perles pour faire un collier.","zh":"她串珠子做項鍊。"},{"s":"Le bracelet est fait de perles colorées.","zh":"這條手鍊是用彩色串珠做的。"}]},"ja":{"word":"ビーズ","kana":"ビーズ","romaji":"bīzu","examples":[{"s":"色とりどりのビーズを糸に通す。","zh":"她把彩色珠子串在線上。"},{"s":"このネックレスは小さなビーズでできている。","zh":"這條項鍊是用小串珠做的。"}]}},
{"id":"p0209","de":{"word":"der Schnabel","ipa":"[ˈʃnaːbl̩]","examples":[{"s":"Der Vogel putzt seine Federn mit dem Schnabel.","zh":"鳥用鳥喙整理羽毛。"},{"s":"Der Specht hackt mit seinem Schnabel am Baum.","zh":"啄木鳥用鳥喙啄樹。"}]},"fr":{"word":"le bec","ipa":"[lə bɛk]","examples":[{"s":"L'oiseau lisse ses plumes avec son bec.","zh":"鳥用鳥喙整理羽毛。"},{"s":"Le moineau tient une graine dans son bec.","zh":"麻雀嘴裡叼著一粒種子。"}]},"ja":{"word":"くちばし","kana":"くちばし","romaji":"kuchibashi","examples":[{"s":"鳥がくちばしで羽づくろいをしている。","zh":"鳥用鳥喙整理羽毛。"},{"s":"すずめがくちばしで種をくわえている。","zh":"麻雀用鳥喙叼著種子。"}]}},
{"id":"p0210","de":{"word":"der Balken","ipa":"[ˈbalkn̩]","examples":[{"s":"Der Balken trägt das Dach des alten Hauses.","zh":"這根橫樑支撐著老屋的屋頂。"},{"s":"Über der Tür hängt ein schwerer Holzbalken.","zh":"門上方懸著一根沉重的木樑。"}]},"fr":{"word":"la poutre","ipa":"[la putʁ]","examples":[{"s":"La poutre soutient le plafond de la grange.","zh":"這根橫樑支撐著穀倉的天花板。"},{"s":"Une vieille poutre en bois traverse le plafond.","zh":"一根老木樑橫貫天花板。"}]},"ja":{"word":"梁","kana":"はり","romaji":"hari","examples":[{"s":"太い梁が古い家の屋根を支えている。","zh":"粗壯的橫樑支撐著老屋的屋頂。"},{"s":"天井に木の梁が渡してある。","zh":"天花板上架著木樑。"}]}},
{"id":"p0211","de":{"word":"das Biest","ipa":"[biːst]","examples":[{"s":"In der Legende lebt ein gefährliches Biest im Wald.","zh":"傳說中森林裡住著一頭危險的野獸。"},{"s":"Das riesige Biest brüllte laut.","zh":"那頭巨大的怪獸大聲吼叫。"}]},"fr":{"word":"la bête","ipa":"[la bɛt]","examples":[{"s":"Une bête féroce rôde dans la forêt.","zh":"一頭兇猛的野獸在森林裡遊蕩。"},{"s":"Les villageois avaient peur de la bête.","zh":"村民們害怕那頭怪獸。"}]},"ja":{"word":"獣","kana":"けもの","romaji":"kemono","examples":[{"s":"森には恐ろしい獣が住んでいる。","zh":"森林裡住著可怕的野獸。"},{"s":"巨大な獣が大きな声で吠えた。","zh":"巨大的怪獸大聲吼叫。"}]}},
{"id":"p0212","de":{"word":"der Takt","ipa":"[takt]","examples":[{"s":"Die Tänzer bewegen sich im Takt der Musik.","zh":"舞者隨著音樂的拍子擺動。"},{"s":"Klopf mit dem Fuß den Takt mit.","zh":"用腳打拍子跟著節拍。"}]},"fr":{"word":"le rythme","ipa":"[lə ʁitm]","examples":[{"s":"Tout le monde danse au rythme de la chanson.","zh":"大家隨著歌曲的拍子跳舞。"},{"s":"Il tape du pied pour suivre le rythme.","zh":"他用腳打拍子跟上節拍。"}]},"ja":{"word":"拍子","kana":"ひょうし","romaji":"hyōshi","examples":[{"s":"ダンサーは音楽の拍子に合わせて動く。","zh":"舞者隨著音樂的拍子擺動。"},{"s":"足で拍子を取りながら歌った。","zh":"我一邊用腳打拍子一邊唱歌。"}]}},
{"id":"p0213","de":{"word":"schön","ipa":"[ʃøːn]","examples":[{"s":"Der Sonnenuntergang am Meer ist wunderschön.","zh":"海邊的日落非常美麗。"},{"s":"Sie trägt heute ein schönes Kleid.","zh":"她今天穿了一件美麗的洋裝。"}]},"fr":{"word":"beau","ipa":"[bo]","examples":[{"s":"Quel beau coucher de soleil ce soir !","zh":"今晚的日落真美麗！"},{"s":"Elle porte une belle robe rouge.","zh":"她穿著一件美麗的紅洋裝。"}]},"ja":{"word":"美しい","kana":"うつくしい","romaji":"utsukushii","examples":[{"s":"海に沈む夕日はとても美しい。","zh":"沉入海裡的夕陽非常美麗。"},{"s":"彼女は美しいドレスを着ている。","zh":"她穿著一件美麗的洋裝。"}]}},
{"id":"p0214","de":{"word":"das Bett","ipa":"[bɛt]","examples":[{"s":"Ich gehe jetzt ins Bett, ich bin müde.","zh":"我累了，現在要去睡覺（上床）。"},{"s":"Das Bett im Hotel war sehr bequem.","zh":"旅館的床很舒服。"}]},"fr":{"word":"le lit","ipa":"[lə li]","examples":[{"s":"Je vais au lit, je suis fatigué.","zh":"我累了，要去睡覺（上床）。"},{"s":"Le lit de cette chambre est très confortable.","zh":"這間房的床很舒服。"}]},"ja":{"word":"ベッド","kana":"ベッド","romaji":"beddo","examples":[{"s":"疲れたのでもうベッドに入る。","zh":"我累了，要上床睡覺。"},{"s":"ホテルのベッドはとても寝心地がよかった。","zh":"旅館的床睡起來很舒服。"}]}},
{"id":"p0215","de":{"word":"das Schlafzimmer","ipa":"[ˈʃlaːfˌt͡sɪmɐ]","examples":[{"s":"Mein Schlafzimmer ist ruhig und gemütlich.","zh":"我的臥室安靜又舒適。"},{"s":"Im Schlafzimmer steht ein großer Schrank.","zh":"臥室裡有一個大衣櫃。"}]},"fr":{"word":"la chambre","ipa":"[la ʃɑ̃bʁ]","examples":[{"s":"Ma chambre donne sur le jardin.","zh":"我的臥室面向花園。"},{"s":"Il range ses vêtements dans la chambre.","zh":"他把衣服收在臥室裡。"}]},"ja":{"word":"寝室","kana":"しんしつ","romaji":"shinshitsu","examples":[{"s":"私の寝室は静かで居心地がいい。","zh":"我的臥室安靜又舒適。"},{"s":"寝室に大きなクローゼットがある。","zh":"臥室裡有一個大衣櫃。"}]}},
{"id":"p0216","de":{"word":"die Schlafenszeit","ipa":"[ˈʃlaːfn̩sˌt͡saɪ̯t]","examples":[{"s":"Es ist Schlafenszeit für die Kinder.","zh":"孩子們該就寢了。"},{"s":"Vor der Schlafenszeit lese ich meiner Tochter vor.","zh":"就寢時間前我會念故事給女兒聽。"}]},"fr":{"word":"l'heure du coucher","ipa":"[lœʁ dy kuʃe]","examples":[{"s":"C'est l'heure du coucher, les enfants.","zh":"孩子們，就寢時間到了。"},{"s":"On lit une histoire avant l'heure du coucher.","zh":"就寢時間前我們會讀一個故事。"}]},"ja":{"word":"寝る時間","kana":"ねるじかん","romaji":"neru jikan","examples":[{"s":"子どもたちはもう寝る時間だ。","zh":"孩子們該就寢了。"},{"s":"寝る時間の前に絵本を読む。","zh":"就寢時間前會讀繪本。"}]}},
{"id":"p0217","de":{"word":"die Biene","ipa":"[ˈbiːnə]","examples":[{"s":"Eine Biene summt um die Blume herum.","zh":"一隻蜜蜂在花朵周圍嗡嗡飛。"},{"s":"Bienen sammeln Nektar für den Honig.","zh":"蜜蜂採集花蜜來釀蜂蜜。"}]},"fr":{"word":"l'abeille","ipa":"[labɛj]","examples":[{"s":"Une abeille butine les fleurs du jardin.","zh":"一隻蜜蜂在花園採花蜜。"},{"s":"Les abeilles font du miel.","zh":"蜜蜂釀造蜂蜜。"}]},"ja":{"word":"蜂","kana":"はち","romaji":"hachi","examples":[{"s":"蜂が花の周りを飛んでいる。","zh":"蜜蜂在花朵周圍飛。"},{"s":"蜂は蜜を集めてはちみつを作る。","zh":"蜜蜂採蜜釀成蜂蜜。"}]}},
{"id":"p0218","de":{"word":"das Rindfleisch","ipa":"[ˈʁɪntˌflaɪ̯ʃ]","examples":[{"s":"Zum Abendessen gibt es geschmortes Rindfleisch.","zh":"晚餐吃燉牛肉。"},{"s":"Ich kaufe frisches Rindfleisch beim Metzger.","zh":"我在肉舖買新鮮牛肉。"}]},"fr":{"word":"le bœuf","ipa":"[lə bœf]","examples":[{"s":"On mange du bœuf braisé ce soir.","zh":"今晚我們吃燉牛肉。"},{"s":"J'achète du bœuf frais chez le boucher.","zh":"我在肉舖買新鮮牛肉。"}]},"ja":{"word":"牛肉","kana":"ぎゅうにく","romaji":"gyūniku","examples":[{"s":"今夜は牛肉の煮込みを食べる。","zh":"今晚吃燉牛肉。"},{"s":"肉屋で新鮮な牛肉を買った。","zh":"我在肉舖買了新鮮牛肉。"}]}},
{"id":"p0219","de":{"word":"das Bier","ipa":"[biːɐ̯]","examples":[{"s":"Wir trinken ein kaltes Bier im Garten.","zh":"我們在花園喝杯冰啤酒。"},{"s":"Zum Grillen gehört ein gutes Bier.","zh":"烤肉配上一杯好啤酒最對味。"}]},"fr":{"word":"la bière","ipa":"[la bjɛʁ]","examples":[{"s":"On boit une bière fraîche sur la terrasse.","zh":"我們在露臺喝杯冰啤酒。"},{"s":"Il commande une bière au bar.","zh":"他在酒吧點了一杯啤酒。"}]},"ja":{"word":"ビール","kana":"ビール","romaji":"bīru","examples":[{"s":"庭で冷たいビールを飲む。","zh":"我們在花園喝冰啤酒。"},{"s":"バーでビールを一杯注文した。","zh":"他在酒吧點了一杯啤酒。"}]}},
{"id":"p0220","de":{"word":"der Käfer","ipa":"[ˈkɛːfɐ]","examples":[{"s":"Ein kleiner Käfer krabbelt über das Blatt.","zh":"一隻小甲蟲在葉子上爬。"},{"s":"Im Garten habe ich einen glänzenden Käfer gefunden.","zh":"我在花園發現了一隻閃亮的甲蟲。"}]},"fr":{"word":"le scarabée","ipa":"[lə skaʁabe]","examples":[{"s":"Un scarabée grimpe sur la feuille.","zh":"一隻甲蟲爬上葉子。"},{"s":"J'ai trouvé un scarabée brillant dans le jardin.","zh":"我在花園裡發現一隻閃亮的甲蟲。"}]},"ja":{"word":"甲虫","kana":"こうちゅう","romaji":"kōchū","examples":[{"s":"小さな甲虫が葉の上を這っている。","zh":"一隻小甲蟲在葉子上爬。"},{"s":"庭で光沢のある甲虫を見つけた。","zh":"我在花園發現一隻閃亮的甲蟲。"}]}}
]
